html_xblock/__init__.py
html_xblock/bleaching.py
html_xblock/html.py
html_xblock/utils.py
html_xblock/public/plugins/codesample/plugin.min.js
html_xblock/public/plugins/codesample/css/prism.css
html_xblock/public/plugins/codesample/js/prism.js
html_xblock/static/css/html_edit.css
html_xblock/static/css/html_preview.css
html_xblock/static/html/lms.html
html_xblock/static/html/studio.html
html_xblock/static/js/html_edit.js
html_xblock-2.0.0.dist-info/LICENSE
html_xblock-2.0.0.dist-info/METADATA
html_xblock-2.0.0.dist-info/WHEEL
html_xblock-2.0.0.dist-info/entry_points.txt
html_xblock-2.0.0.dist-info/top_level.txt
html_xblock-2.0.0.dist-info/RECORD
