Metadata-Version: 2.2
Name: html-xblock
Version: 2.0.0
Summary: HTML XBlock will help creating and using a secure and easy-to-use HTML blocks
Home-page: https://github.com/open-craft/xblock-html
Author: OpenCraft
License: AGPL v3
Keywords: Python edx
Requires-Python: >=3.11
License-File: LICENSE
Requires-Dist: Django
Requires-Dist: bleach[css]
Requires-Dist: xblock[django]
Dynamic: author
Dynamic: description
Dynamic: description-content-type
Dynamic: home-page
Dynamic: keywords
Dynamic: license
Dynamic: requires-dist
Dynamic: requires-python
Dynamic: summary
